causalem/__init__.py
causalem/_experimental/__init__.py
causalem/_experimental/cate.py
causalem/datasets/__init__.py
causalem/datasets/lalonde.csv
causalem/datasets/tof_survival.csv
causalem/datasets/tof_survival_with_mediator.csv
causalem/design/__init__.py
causalem/design/diagnostics.py
causalem/design/matchers.py
causalem/estimation/__init__.py
causalem/estimation/ensemble.py
causalem/mediation/__init__.py
causalem/mediation/_experimental.py
causalem/utils/__init__.py
causalem/utils/_survival.py
causalem/utils/_weights.py
causalem-1.3.0.dist-info/licenses/LICENSE
causalem-1.3.0.dist-info/METADATA
causalem-1.3.0.dist-info/WHEEL
causalem-1.3.0.dist-info/top_level.txt
causalem-1.3.0.dist-info/RECORD
