Metadata-Version: 2.4
Name: causalem
Version: 1.3.0
Summary: Causal Inference using Ensemble Matching
Author-email: "Alireza S. Mahani, Mansour T.A. Sharabiani" <alireza.s.mahani@gmail.com>
License: MIT License
Keywords: causal-inference,matching,ensemble learning
Classifier: Programming Language :: Python :: 3
Classifier: License :: OSI Approved :: MIT License
Classifier: Operating System :: OS Independent
Requires-Python: >=3.9
License-File: LICENSE
Requires-Dist: numpy>=1.23
Requires-Dist: pandas>=2.0
Requires-Dist: scikit-learn>=1.3
Requires-Dist: joblib>=1.2
Requires-Dist: matplotlib>=3.5
Requires-Dist: tqdm>=4.0
Requires-Dist: statsmodels>=0.14
Requires-Dist: scikit-survival
Provides-Extra: dev
Requires-Dist: pytest>=7.0; extra == "dev"
Requires-Dist: pytest-xdist>=3.0; extra == "dev"
Requires-Dist: ruff>=0.11.7; extra == "dev"
Requires-Dist: mypy>=1.5; extra == "dev"
Requires-Dist: pre-commit>=2.20; extra == "dev"
Requires-Dist: sphinx>=6.0; extra == "dev"
Requires-Dist: sphinx-autobuild; extra == "dev"
Requires-Dist: sphinx-rtd-theme; extra == "dev"
Dynamic: license-file
